sodiumfrp/__init__.py
sodiumfrp/lazy.py
sodiumfrp/listener.py
sodiumfrp/node.py
sodiumfrp/operational.py
sodiumfrp/primitives.py
sodiumfrp/py.typed
sodiumfrp/time.py
sodiumfrp/transaction.py
sodiumfrp/typing.py
sodiumfrp/unit.py
tests/__init__.py
tests/memory1.py
tests/memory3.py
tests/memory4.py
tests/memory5.py
tests/test_cell.py
tests/test_common.py
tests/test_stream.py
tests/test_time.py
tests/test_transaction.py
sodiumfrp-1.0.1.dist-info/METADATA
sodiumfrp-1.0.1.dist-info/WHEEL
sodiumfrp-1.0.1.dist-info/top_level.txt
sodiumfrp-1.0.1.dist-info/RECORD
