Metadata-Version: 2.1
Name: sodiumfrp
Version: 1.0.1
Summary: Python implementation of Sodium - Functional Reactive Programming (FRP) library
Home-page: https://github.com/mode89/sodium-python
Author: Stephen Blackheath
License: BSD-3 License
Classifier: Programming Language :: Python :: 3
Classifier: License :: OSI Approved :: BSD License
Classifier: Operating System :: OS Independent
Requires-Python: >=3.6
